{
  "Stage": "M2",
  "Status": "PASS",
  "ErrorMessage": null,
  "ErrorHResult": null,
  "ElapsedMs": 301,
  "D3D11CreateDeviceHr": "0x00000000",
  "DxgiDeviceQiHr": null,
  "CreateDirect3DDeviceHr": "0x00000000",
  "AdapterName": null,
  "AdapterLuid": null,
  "CaptureItemWidth": 2560,
  "CaptureItemHeight": 1600,
  "FrameReceived": true,
  "SurfaceNotNull": true,
  "FrameWidth": 2560,
  "FrameHeight": 1600,
  "CallbackThreadId": 4,
  "AsInteropSuccess": true,
  "GetInterfaceHr": "0x00000000",
  "TextureWidth": 2560,
  "TextureHeight": 1600,
  "TextureFormat": "DXGI_FORMAT_B8G8R8A8_UNORM",
  "TextureMipLevels": 1,
  "TextureArraySize": 1,
  "MapSuccess": true,
  "BmpExists": true,
  "BmpSize": 16384054
}